{
  "root_dir": "C:\\Users\\fa-tj\\Desktop\\Simulador WEB e conversores\\Simuladores WEB\\CANON",
  "root_main": "Simulador.pptx",
  "arquivos": [
    {
      "arquivo": "Abdome - Toshiba (Canon).pptx",
      "saida": "abdome_toshiba_canon",
      "tipo": "aula",
      "menu_url": "../index.html",
      "portal_url": "../index.html"
    },
    {
      "arquivo": "ATM - Toshiba (Canon).pptx",
      "saida": "atm_toshiba_canon",
      "tipo": "aula",
      "menu_url": "../index.html",
      "portal_url": "../index.html"
    },
    {
      "arquivo": "C. Torácica - Toshiba (Canon).pptx",
      "saida": "c_toracica_toshiba_canon",
      "tipo": "aula",
      "menu_url": "../index.html",
      "portal_url": "../index.html"
    },
    {
      "arquivo": "Cervical - Toshiba (Canon).pptx",
      "saida": "cervical_toshiba_canon",
      "tipo": "aula",
      "menu_url": "../index.html",
      "portal_url": "../index.html"
    },
    {
      "arquivo": "Cotovelo - Toshiba (Canon).pptx",
      "saida": "cotovelo_toshiba_canon",
      "tipo": "aula",
      "menu_url": "../index.html",
      "portal_url": "../index.html"
    },
    {
      "arquivo": "CRANIO - Toshiba (Canon).pptx",
      "saida": "cranio_toshiba_canon",
      "tipo": "aula",
      "menu_url": "../index.html",
      "portal_url": "../index.html"
    },
    {
      "arquivo": "Face - Toshiba (Canon).pptx",
      "saida": "face_toshiba_canon",
      "tipo": "aula",
      "menu_url": "../index.html",
      "portal_url": "../index.html"
    },
    {
      "arquivo": "Hipófise, Sela Turca - Toshiba (Canon).pptx",
      "saida": "hipofise_sela_turca_toshiba_canon",
      "tipo": "aula",
      "menu_url": "../index.html",
      "portal_url": "../index.html"
    },
    {
      "arquivo": "Joelho - Toshiba (Canon).pptx",
      "saida": "joelho_toshiba_canon",
      "tipo": "aula",
      "menu_url": "../index.html",
      "portal_url": "../index.html"
    },
    {
      "arquivo": "Mastoide - Toshiba (Canon).pptx",
      "saida": "mastoide_toshiba_canon",
      "tipo": "aula",
      "menu_url": "../index.html",
      "portal_url": "../index.html"
    },
    {
      "arquivo": "Ombro - Toshiba (Canon).pptx",
      "saida": "ombro_toshiba_canon",
      "tipo": "aula",
      "menu_url": "../index.html",
      "portal_url": "../index.html"
    },
    {
      "arquivo": "Pescoço - Toshiba (Canon).pptx",
      "saida": "pescoco_toshiba_canon",
      "tipo": "aula",
      "menu_url": "../index.html",
      "portal_url": "../index.html"
    },
    {
      "arquivo": "Punho ou mão - Toshiba (Canon).pptx",
      "saida": "punho_ou_mao_toshiba_canon",
      "tipo": "aula",
      "menu_url": "../index.html",
      "portal_url": "../index.html"
    },
    {
      "arquivo": "Pé - Toshiba (Canon).pptx",
      "saida": "pe_toshiba_canon",
      "tipo": "aula",
      "menu_url": "../index.html",
      "portal_url": "../index.html"
    },
    {
      "arquivo": "Seios da face - Toshiba (Canon).pptx",
      "saida": "seios_da_face_toshiba_canon",
      "tipo": "aula",
      "menu_url": "../index.html",
      "portal_url": "../index.html"
    },
    {
      "arquivo": "Tórax - Toshiba (Canon).pptx",
      "saida": "torax_toshiba_canon",
      "tipo": "aula",
      "menu_url": "../index.html",
      "portal_url": "../index.html"
    },
    {
      "arquivo": "Órbitas - Toshiba (Canon).pptx",
      "saida": "orbitas_toshiba_canon",
      "tipo": "aula",
      "menu_url": "../index.html",
      "portal_url": "../index.html"
    },
    {
      "arquivo": "Simulador.pptx",
      "saida": ".",
      "tipo": "root_main",
      "menu_url": "index.html",
      "portal_url": "index.html"
    }
  ],
  "mains_detectados": [
    {
      "pasta": ".",
      "main": "Simulador.pptx"
    }
  ],
  "falhas": []
}